youtube_indirici/indir.py
youtube_indirici_atilla-29.9.2025.4.2.dist-info/METADATA
youtube_indirici_atilla-29.9.2025.4.2.dist-info/WHEEL
youtube_indirici_atilla-29.9.2025.4.2.dist-info/entry_points.txt
youtube_indirici_atilla-29.9.2025.4.2.dist-info/top_level.txt
youtube_indirici_atilla-29.9.2025.4.2.dist-info/RECORD
