Metadata-Version: 2.4
Name: youtube-indirici-atilla
Version: 29.9.2025.4.2
Summary: Komut satırından YouTube videolarını MP4 olarak indirmek için basit ama güçlü bir Python paketi.
Author: Atilla, Python Kod Asistanı (Gemini)
Keywords: youtube,indirici,yt-dlp,gui
Classifier: Programming Language :: Python :: 3
Classifier: License :: OSI Approved :: MIT License
Classifier: Operating System :: OS Independent
Requires-Python: >=3.13
Requires-Dist: yt-dlp
Requires-Dist: Pillow
